{
   "CBC": {
      "time": 279,
      "optimal": true,
      "objective": 226,
      "solution": [
         [
            3
         ],
         [
            7,
            2
         ],
         [
            8
         ],
         [
            6
         ],
         [
            5,
            9
         ],
         [
            4,
            1
         ]
      ]
   },
   "HiGHS": {
      "time": 7,
      "optimal": true,
      "objective": 226,
      "solution": [
         [
            2
         ],
         [
            3
         ],
         [
            1
         ],
         [
            4
         ],
         [
            8,
            6,
            9
         ],
         [
            5,
            7
         ]
      ]
   }
}