{
   "CBC": {
      "time": 95,
      "optimal": true,
      "objective": 322,
      "solution": [
         [
            6
         ],
         [
            8,
            1
         ],
         [
            5,
            7
         ],
         [
            2
         ],
         [
            3
         ],
         [
            4
         ]
      ]
   },
   "HiGHS": {
      "time": 7,
      "optimal": true,
      "objective": 322,
      "solution": [
         [
            6
         ],
         [
            1,
            8,
            4
         ],
         [
            2
         ],
         [
            3
         ],
         [
            5
         ],
         [
            7
         ]
      ]
   }
}